satcompression/__init__.py
satcompression/compress_node.py
satcompression/image_compressor.py
satcompression/main.py
satcompression/quadtree.py
satcompression/reconstruct_node.py
satcompression/utils.py
satcompression-0.0.3.dist-info/LICENSE
satcompression-0.0.3.dist-info/WHEEL
satcompression-0.0.3.dist-info/METADATA
satcompression-0.0.3.dist-info/RECORD
