Metadata-Version: 2.1
Name: satcompression
Version: 0.0.3
Summary: A python package to compress sat data
Home-page: https://github.com/csaybar/satcompression
Author: Cesar Aybar
Author-email: fcesar.aybar@gmail.com
Requires-Python: >=3.9,<4.0
Classifier: Programming Language :: Python :: 3
Classifier: Programming Language :: Python :: 3.9
Classifier: Programming Language :: Python :: 3.10
Requires-Dist: numpy (>=1.25.2)
Requires-Dist: sortedcontainers (>=2.4.0)
Requires-Dist: tqdm (>=4.66.4)
Project-URL: Documentation, https://csaybar.github.io/satcompression/
Project-URL: Repository, https://github.com/csaybar/satcompression
